{
	"configurations" : 
	[
		{
			"directories" : 
			[
				{
					"build" : ".",
					"childIndexes" : 
					[
						1,
						2,
						3
					],
					"jsonFile" : "directory-.-Debug-f5ebdc15457944623624.json",
					"minimumCMakeVersion" : 
					{
						"string" : "3.13"
					},
					"projectIndex" : 0,
					"source" : ".",
					"targetIndexes" : 
					[
						0
					]
				},
				{
					"build" : "OPSQLiteSpec_autolinked_build",
					"jsonFile" : "directory-OPSQLiteSpec_autolinked_build-Debug-13058f44fab6fdd53f93.json",
					"minimumCMakeVersion" : 
					{
						"string" : "3.13"
					},
					"parentIndex" : 0,
					"projectIndex" : 0,
					"source" : "/Users/okihita/ArcaneSanctum/ARM-AI-Hackathon/mobile/node_modules/@op-engineering/op-sqlite/android/build/generated/source/codegen/jni",
					"targetIndexes" : 
					[
						1
					]
				},
				{
					"build" : "RNLlamaSpec_autolinked_build",
					"jsonFile" : "directory-RNLlamaSpec_autolinked_build-Debug-db7cde8048f19abf4ced.json",
					"minimumCMakeVersion" : 
					{
						"string" : "3.13"
					},
					"parentIndex" : 0,
					"projectIndex" : 0,
					"source" : "/Users/okihita/ArcaneSanctum/ARM-AI-Hackathon/mobile/node_modules/llama.rn/android/build/generated/source/codegen/jni",
					"targetIndexes" : 
					[
						2
					]
				},
				{
					"build" : "safeareacontext_autolinked_build",
					"jsonFile" : "directory-safeareacontext_autolinked_build-Debug-d077455bd1632bcb145b.json",
					"minimumCMakeVersion" : 
					{
						"string" : "3.13"
					},
					"parentIndex" : 0,
					"projectIndex" : 0,
					"source" : "/Users/okihita/ArcaneSanctum/ARM-AI-Hackathon/mobile/node_modules/react-native-safe-area-context/android/src/main/jni",
					"targetIndexes" : 
					[
						3
					]
				}
			],
			"name" : "Debug",
			"projects" : 
			[
				{
					"directoryIndexes" : 
					[
						0,
						1,
						2,
						3
					],
					"name" : "appmodules",
					"targetIndexes" : 
					[
						0,
						1,
						2,
						3
					]
				}
			],
			"targets" : 
			[
				{
					"directoryIndex" : 0,
					"id" : "appmodules::@6890427a1f51a3e7e1df",
					"jsonFile" : "target-appmodules-Debug-23a8ce9d000bb52e62b8.json",
					"name" : "appmodules",
					"projectIndex" : 0
				},
				{
					"directoryIndex" : 1,
					"id" : "react_codegen_OPSQLiteSpec::@1d2ceb4ab0c4d2e06808",
					"jsonFile" : "target-react_codegen_OPSQLiteSpec-Debug-f886c6df9cf2682088be.json",
					"name" : "react_codegen_OPSQLiteSpec",
					"projectIndex" : 0
				},
				{
					"directoryIndex" : 2,
					"id" : "react_codegen_RNLlamaSpec::@3011804ba7033a5dd5ff",
					"jsonFile" : "target-react_codegen_RNLlamaSpec-Debug-5d1b8f4f7e4133cab5b2.json",
					"name" : "react_codegen_RNLlamaSpec",
					"projectIndex" : 0
				},
				{
					"directoryIndex" : 3,
					"id" : "react_codegen_safeareacontext::@7984cd80db47aa7b952a",
					"jsonFile" : "target-react_codegen_safeareacontext-Debug-38dafb39d181117d81e2.json",
					"name" : "react_codegen_safeareacontext",
					"projectIndex" : 0
				}
			]
		}
	],
	"kind" : "codemodel",
	"paths" : 
	{
		"build" : "/Users/okihita/ArcaneSanctum/ARM-AI-Hackathon/mobile/android/app/.cxx/Debug/c4x11r4x/arm64-v8a",
		"source" : "/Users/okihita/ArcaneSanctum/ARM-AI-Hackathon/mobile/node_modules/react-native/ReactAndroid/cmake-utils/default-app-setup"
	},
	"version" : 
	{
		"major" : 2,
		"minor" : 3
	}
}
